{
	"data": [
		{
			"ID": 752865,
			"ShopID": 58,
			"Suggestions": null,
			"SKU": "8888021200126",
			"IsSKUCorrect": 1,
			"Ignored": false,
			"Name": "סוללות דבאל a",
			"Tags": "[{\"id\":18,\"name\":\"סוללות (Batteries)\"}]",
			"Image": null,
			"ProductImage": "8888021200126.png",
			"ImageToShow": "8888021200126.png",
			"FirstUnitMeasureID": 8,
			"FirstUnitMeasureName": "Unit",
			"FirstUnitMeasureDisplayName": "יח׳",
			"FirstUnitMeasureNameTranslations": null,
			"FirstUnitWeight": 0,
			"SecondUnitMeasureID": null,
			"SecondUnitMeasureName": null,
			"SecondUnitMeasureDisplayName": null,
			"SecondUnitMeasureNameTranslations": null,
			"SecondUnitWeight": 0,
			"Price": 16.9,
			"OldPrice": "14.90",
			"UnlimitedQuantity": true,
			"Quantity": 0,
			"LowestPriceInShoook": 0,
			"DisplayOrder": null,
			"OrderForPicking": 9999,
			"ShowInStock": false,
			"ProductID": 98361,
			"ProductName": "מארז סוללות פורמולה AA",
			"ProductSKU": "8888021200126",
			"ProductManufacturerName": "דנסל",
			"ProductBrandName": "אנרגיזר",
			"ManufacturerName": null,
			"ManufacturerID": 0,
			"BrandName": null,
			"BrandID": 0,
			"ShopName": "Opal Market",
			"SoldByWeight": false,
			"PrivateText": null,
			"CommentsForAdmin": null,
			"EnableOverrideGlobal": false,
			"IsMeasuredBySKU": false,
			"Capacity": null,
			"LinkedImages": [],
			"AddNewForm": null,
			"ControllerName": null,
			"Editable": true,
			"Moveable": false,
			"Popup": false,
			"ToggelActive": false,
			"Copy": false,
			"Delete": false,
			"HasInvoice": false,
			"ForNames": false
		},
		{
			"ID": 767475,
			"ShopID": 58,
			"Suggestions": null,
			"SKU": "8888021200164",
			"IsSKUCorrect": 1,
			"Ignored": false,
			"Name": "מארז סוללות פורמולה AAA",
			"Tags": "[{\"id\":18,\"name\":\"סוללות (Batteries)\"},{\"id\":123,\"name\":\"כלי בית  וג'אדג'טים (HousewaresGadgets)\"}]",
			"Image": null,
			"ProductImage": "8888021200164.png",
			"ImageToShow": "8888021200164.png",
			"FirstUnitMeasureID": 8,
			"FirstUnitMeasureName": "Unit",
			"FirstUnitMeasureDisplayName": "יח׳",
			"FirstUnitMeasureNameTranslations": null,
			"FirstUnitWeight": 0,
			"SecondUnitMeasureID": null,
			"SecondUnitMeasureName": null,
			"SecondUnitMeasureDisplayName": null,
			"SecondUnitMeasureNameTranslations": null,
			"SecondUnitWeight": 0,
			"Price": 14.9,
			"OldPrice": null,
			"UnlimitedQuantity": true,
			"Quantity": 0,
			"LowestPriceInShoook": 0,
			"DisplayOrder": 9999,
			"OrderForPicking": 9999,
			"ShowInStock": false,
			"ProductID": 98362,
			"ProductName": "מארז סוללות פורמולה AAA",
			"ProductSKU": "8888021200164",
			"ProductManufacturerName": "דנסל",
			"ProductBrandName": "אנרג'יזר",
			"ManufacturerName": null,
			"ManufacturerID": null,
			"BrandName": null,
			"BrandID": 0,
			"ShopName": "Opal Market",
			"SoldByWeight": false,
			"PrivateText": "",
			"CommentsForAdmin": null,
			"EnableOverrideGlobal": false,
			"IsMeasuredBySKU": true,
			"Capacity": "0",
			"LinkedImages": [],
			"AddNewForm": null,
			"ControllerName": null,
			"Editable": true,
			"Moveable": false,
			"Popup": false,
			"ToggelActive": false,
			"Copy": false,
			"Delete": false,
			"HasInvoice": false,
			"ForNames": false
		},
		{
			"ID": 753082,
			"ShopID": 58,
			"Suggestions": null,
			"SKU": "8934878081712",
			"IsSKUCorrect": 1,
			"Ignored": false,
			"Name": "אטריות אורז 450ג",
			"Tags": "[{\"id\":145,\"name\":\"אטריות (Noodles)\"}]",
			"Image": null,
			"ProductImage": null,
			"ImageToShow": null,
			"FirstUnitMeasureID": 3,
			"FirstUnitMeasureName": "Gram",
			"FirstUnitMeasureDisplayName": "גרם",
			"FirstUnitMeasureNameTranslations": null,
			"FirstUnitWeight": 0,
			"SecondUnitMeasureID": null,
			"SecondUnitMeasureName": null,
			"SecondUnitMeasureDisplayName": null,
			"SecondUnitMeasureNameTranslations": null,
			"SecondUnitWeight": 0,
			"Price": 11.9,
			"OldPrice": null,
			"UnlimitedQuantity": false,
			"Quantity": 0,
			"LowestPriceInShoook": 0,
			"DisplayOrder": null,
			"OrderForPicking": 9999,
			"ShowInStock": false,
			"ProductID": 148840,
			"ProductName": "אטריות אורז 5 מ\"מ ללא גלוטן",
			"ProductSKU": "8934878081712",
			"ProductManufacturerName": "chanh khang company",
			"ProductBrandName": "מזרח ומערב",
			"ManufacturerName": null,
			"ManufacturerID": 0,
			"BrandName": null,
			"BrandID": 0,
			"ShopName": "Opal Market",
			"SoldByWeight": false,
			"PrivateText": null,
			"CommentsForAdmin": null,
			"EnableOverrideGlobal": false,
			"IsMeasuredBySKU": false,
			"Capacity": null,
			"LinkedImages": [],
			"AddNewForm": null,
			"ControllerName": null,
			"Editable": true,
			"Moveable": false,
			"Popup": false,
			"ToggelActive": false,
			"Copy": false,
			"Delete": false,
			"HasInvoice": false,
			"ForNames": false
		},
		{
			"ID": 752803,
			"ShopID": 58,
			"Suggestions": null,
			"SKU": "9322969000015",
			"IsSKUCorrect": 1,
			"Ignored": false,
			"Name": "פריכיות תירס טעם אורגינלי 150 ג",
			"Tags": "[{\"id\":57,\"name\":\"קרקרים ופרכיות (Crackers)\"}]",
			"Image": null,
			"ProductImage": "9322969000015.png",
			"ImageToShow": "9322969000015.png",
			"FirstUnitMeasureID": 3,
			"FirstUnitMeasureName": "Gram",
			"FirstUnitMeasureDisplayName": "גרם",
			"FirstUnitMeasureNameTranslations": null,
			"FirstUnitWeight": 0,
			"SecondUnitMeasureID": null,
			"SecondUnitMeasureName": null,
			"SecondUnitMeasureDisplayName": null,
			"SecondUnitMeasureNameTranslations": null,
			"SecondUnitWeight": 0,
			"Price": 15.5,
			"OldPrice": "15.90",
			"UnlimitedQuantity": true,
			"Quantity": 0,
			"LowestPriceInShoook": 0,
			"DisplayOrder": null,
			"OrderForPicking": 9999,
			"ShowInStock": false,
			"ProductID": 78922,
			"ProductName": "פריכיות תירס טעם טבעי",
			"ProductSKU": "9322969000015",
			"ProductManufacturerName": "אלגם גיל",
			"ProductBrandName": "ריאל פוד",
			"ManufacturerName": null,
			"ManufacturerID": 0,
			"BrandName": null,
			"BrandID": 0,
			"ShopName": "Opal Market",
			"SoldByWeight": false,
			"PrivateText": null,
			"CommentsForAdmin": null,
			"EnableOverrideGlobal": false,
			"IsMeasuredBySKU": false,
			"Capacity": null,
			"LinkedImages": [],
			"AddNewForm": null,
			"ControllerName": null,
			"Editable": true,
			"Moveable": false,
			"Popup": false,
			"ToggelActive": false,
			"Copy": false,
			"Delete": false,
			"HasInvoice": false,
			"ForNames": false
		},
		{
			"ID": 752804,
			"ShopID": 58,
			"Suggestions": null,
			"SKU": "9322969000046",
			"IsSKUCorrect": 1,
			"Ignored": false,
			"Name": "פריכיות תירס אורגני",
			"Tags": "[{\"id\":57,\"name\":\"קרקרים ופרכיות (Crackers)\"}]",
			"Image": null,
			"ProductImage": "9322969000046.png",
			"ImageToShow": "9322969000046.png",
			"FirstUnitMeasureID": 3,
			"FirstUnitMeasureName": "Gram",
			"FirstUnitMeasureDisplayName": "גרם",
			"FirstUnitMeasureNameTranslations": null,
			"FirstUnitWeight": 0,
			"SecondUnitMeasureID": null,
			"SecondUnitMeasureName": null,
			"SecondUnitMeasureDisplayName": null,
			"SecondUnitMeasureNameTranslations": null,
			"SecondUnitWeight": 0,
			"Price": 15.5,
			"OldPrice": "15.90",
			"UnlimitedQuantity": true,
			"Quantity": 0,
			"LowestPriceInShoook": 0,
			"DisplayOrder": null,
			"OrderForPicking": 9999,
			"ShowInStock": false,
			"ProductID": 78924,
			"ProductName": "פריכיות תירס אורגניות עם שומשום",
			"ProductSKU": "9322969000046",
			"ProductManufacturerName": "ריאל פודס בעמ",
			"ProductBrandName": "ריאל פוד",
			"ManufacturerName": null,
			"ManufacturerID": 0,
			"BrandName": null,
			"BrandID": 0,
			"ShopName": "Opal Market",
			"SoldByWeight": false,
			"PrivateText": null,
			"CommentsForAdmin": null,
			"EnableOverrideGlobal": false,
			"IsMeasuredBySKU": false,
			"Capacity": null,
			"LinkedImages": [],
			"AddNewForm": null,
			"ControllerName": null,
			"Editable": true,
			"Moveable": false,
			"Popup": false,
			"ToggelActive": false,
			"Copy": false,
			"Delete": false,
			"HasInvoice": false,
			"ForNames": false
		},
		{
			"ID": 678032,
			"ShopID": 58,
			"Suggestions": null,
			"SKU": "936372993637",
			"IsSKUCorrect": -1,
			"Ignored": false,
			"Name": "דני שוקולד שטראוס 125 ג",
			"Tags": "[{\"id\":65,\"name\":\"מעדנים (Delicacies)\"}]",
			"Image": "optimizedמעדןדנישוקולדשטראוס.JPEG.png",
			"ProductImage": "72993637.png",
			"ImageToShow": "optimizedמעדןדנישוקולדשטראוס.JPEG.png",
			"FirstUnitMeasureID": 3,
			"FirstUnitMeasureName": "Gram",
			"FirstUnitMeasureDisplayName": "גרם",
			"FirstUnitMeasureNameTranslations": null,
			"FirstUnitWeight": 0,
			"SecondUnitMeasureID": null,
			"SecondUnitMeasureName": null,
			"SecondUnitMeasureDisplayName": null,
			"SecondUnitMeasureNameTranslations": null,
			"SecondUnitWeight": 0,
			"Price": 3.5,
			"OldPrice": null,
			"UnlimitedQuantity": true,
			"Quantity": 0,
			"LowestPriceInShoook": 0,
			"DisplayOrder": null,
			"OrderForPicking": 9999,
			"ShowInStock": false,
			"ProductID": 227706,
			"ProductName": "מעדן דני שוקולד \"שטראוס\"",
			"ProductSKU": "9363772993637",
			"ProductManufacturerName": "שטראוס חלב ופרי מור",
			"ProductBrandName": "שטראוס",
			"ManufacturerName": null,
			"ManufacturerID": null,
			"BrandName": null,
			"BrandID": null,
			"ShopName": "Opal Market",
			"SoldByWeight": false,
			"PrivateText": null,
			"CommentsForAdmin": null,
			"EnableOverrideGlobal": false,
			"IsMeasuredBySKU": false,
			"Capacity": null,
			"LinkedImages": [],
			"AddNewForm": null,
			"ControllerName": null,
			"Editable": true,
			"Moveable": false,
			"Popup": false,
			"ToggelActive": false,
			"Copy": false,
			"Delete": false,
			"HasInvoice": false,
			"ForNames": false
		},
		{
			"ID": 678334,
			"ShopID": 58,
			"Suggestions": null,
			"SKU": "9771565038326",
			"IsSKUCorrect": 1,
			"Ignored": false,
			"Name": "עיתון",
			"Tags": "[{\"id\":144,\"name\":\"עיתונים/ספרים (NewspapersBooks)\"}]",
			"Image": null,
			"ProductImage": null,
			"ImageToShow": null,
			"FirstUnitMeasureID": 8,
			"FirstUnitMeasureName": "Unit",
			"FirstUnitMeasureDisplayName": "יח׳",
			"FirstUnitMeasureNameTranslations": null,
			"FirstUnitWeight": 0,
			"SecondUnitMeasureID": null,
			"SecondUnitMeasureName": null,
			"SecondUnitMeasureDisplayName": null,
			"SecondUnitMeasureNameTranslations": null,
			"SecondUnitWeight": 0,
			"Price": 5,
			"OldPrice": null,
			"UnlimitedQuantity": false,
			"Quantity": 0,
			"LowestPriceInShoook": 0,
			"DisplayOrder": null,
			"OrderForPicking": 9999,
			"ShowInStock": false,
			"ProductID": 121072,
			"ProductName": "עיתון ידיעות אחרונות יום חול ",
			"ProductSKU": "9771565038326",
			"ProductManufacturerName": "ידיעות אחרונות",
			"ProductBrandName": null,
			"ManufacturerName": null,
			"ManufacturerID": 0,
			"BrandName": null,
			"BrandID": 0,
			"ShopName": "Opal Market",
			"SoldByWeight": false,
			"PrivateText": null,
			"CommentsForAdmin": null,
			"EnableOverrideGlobal": false,
			"IsMeasuredBySKU": false,
			"Capacity": null,
			"LinkedImages": [],
			"AddNewForm": null,
			"ControllerName": null,
			"Editable": true,
			"Moveable": false,
			"Popup": false,
			"ToggelActive": false,
			"Copy": false,
			"Delete": false,
			"HasInvoice": false,
			"ForNames": false
		},
		{
			"ID": 678335,
			"ShopID": 58,
			"Suggestions": null,
			"SKU": "9771565038340",
			"IsSKUCorrect": 1,
			"Ignored": false,
			"Name": "עיתון ידיעות",
			"Tags": "[{\"id\":144,\"name\":\"עיתונים/ספרים (NewspapersBooks)\"}]",
			"Image": null,
			"ProductImage": null,
			"ImageToShow": null,
			"FirstUnitMeasureID": null,
			"FirstUnitMeasureName": null,
			"FirstUnitMeasureDisplayName": null,
			"FirstUnitMeasureNameTranslations": null,
			"FirstUnitWeight": 0,
			"SecondUnitMeasureID": null,
			"SecondUnitMeasureName": null,
			"SecondUnitMeasureDisplayName": null,
			"SecondUnitMeasureNameTranslations": null,
			"SecondUnitWeight": 0,
			"Price": 6,
			"OldPrice": null,
			"UnlimitedQuantity": false,
			"Quantity": 0,
			"LowestPriceInShoook": 0,
			"DisplayOrder": null,
			"OrderForPicking": 9999,
			"ShowInStock": false,
			"ProductID": 75610,
			"ProductName": "ידיעות יום ד",
			"ProductSKU": "9771565038340",
			"ProductManufacturerName": null,
			"ProductBrandName": null,
			"ManufacturerName": null,
			"ManufacturerID": 0,
			"BrandName": null,
			"BrandID": 0,
			"ShopName": "Opal Market",
			"SoldByWeight": false,
			"PrivateText": null,
			"CommentsForAdmin": null,
			"EnableOverrideGlobal": false,
			"IsMeasuredBySKU": false,
			"Capacity": null,
			"LinkedImages": [],
			"AddNewForm": null,
			"ControllerName": null,
			"Editable": true,
			"Moveable": false,
			"Popup": false,
			"ToggelActive": false,
			"Copy": false,
			"Delete": false,
			"HasInvoice": false,
			"ForNames": false
		},
		{
			"ID": 678336,
			"ShopID": 58,
			"Suggestions": null,
			"SKU": "9771565038357",
			"IsSKUCorrect": 1,
			"Ignored": false,
			"Name": "עיתון ידיעות",
			"Tags": "[]",
			"Image": null,
			"ProductImage": null,
			"ImageToShow": null,
			"FirstUnitMeasureID": 8,
			"FirstUnitMeasureName": "Unit",
			"FirstUnitMeasureDisplayName": "יח׳",
			"FirstUnitMeasureNameTranslations": null,
			"FirstUnitWeight": 0,
			"SecondUnitMeasureID": null,
			"SecondUnitMeasureName": null,
			"SecondUnitMeasureDisplayName": null,
			"SecondUnitMeasureNameTranslations": null,
			"SecondUnitWeight": 0,
			"Price": 5,
			"OldPrice": null,
			"UnlimitedQuantity": false,
			"Quantity": 0,
			"LowestPriceInShoook": 0,
			"DisplayOrder": null,
			"OrderForPicking": 9999,
			"ShowInStock": false,
			"ProductID": 75608,
			"ProductName": "ידיעות אחרונות יום ה",
			"ProductSKU": "9771565038357",
			"ProductManufacturerName": null,
			"ProductBrandName": null,
			"ManufacturerName": null,
			"ManufacturerID": 0,
			"BrandName": null,
			"BrandID": 0,
			"ShopName": "Opal Market",
			"SoldByWeight": false,
			"PrivateText": null,
			"CommentsForAdmin": null,
			"EnableOverrideGlobal": false,
			"IsMeasuredBySKU": false,
			"Capacity": null,
			"LinkedImages": [],
			"AddNewForm": null,
			"ControllerName": null,
			"Editable": true,
			"Moveable": false,
			"Popup": false,
			"ToggelActive": false,
			"Copy": false,
			"Delete": false,
			"HasInvoice": false,
			"ForNames": false
		},
		{
			"ID": 678337,
			"ShopID": 58,
			"Suggestions": null,
			"SKU": "9771565051066",
			"IsSKUCorrect": 1,
			"Ignored": false,
			"Name": "עיתון ידיעות אחרונות",
			"Tags": "[{\"id\":144,\"name\":\"עיתונים/ספרים (NewspapersBooks)\"}]",
			"Image": null,
			"ProductImage": null,
			"ImageToShow": null,
			"FirstUnitMeasureID": 8,
			"FirstUnitMeasureName": "Unit",
			"FirstUnitMeasureDisplayName": "יח׳",
			"FirstUnitMeasureNameTranslations": null,
			"FirstUnitWeight": 0,
			"SecondUnitMeasureID": null,
			"SecondUnitMeasureName": null,
			"SecondUnitMeasureDisplayName": null,
			"SecondUnitMeasureNameTranslations": null,
			"SecondUnitWeight": 0,
			"Price": 20,
			"OldPrice": null,
			"UnlimitedQuantity": false,
			"Quantity": 0,
			"LowestPriceInShoook": 0,
			"DisplayOrder": null,
			"OrderForPicking": 9999,
			"ShowInStock": false,
			"ProductID": 75609,
			"ProductName": "ידיעות אחרונות עיתון שישי",
			"ProductSKU": "9771565051066",
			"ProductManufacturerName": "ידיעות אחרונות",
			"ProductBrandName": null,
			"ManufacturerName": null,
			"ManufacturerID": 0,
			"BrandName": null,
			"BrandID": 0,
			"ShopName": "Opal Market",
			"SoldByWeight": false,
			"PrivateText": null,
			"CommentsForAdmin": null,
			"EnableOverrideGlobal": false,
			"IsMeasuredBySKU": false,
			"Capacity": null,
			"LinkedImages": [],
			"AddNewForm": null,
			"ControllerName": null,
			"Editable": true,
			"Moveable": false,
			"Popup": false,
			"ToggelActive": false,
			"Copy": false,
			"Delete": false,
			"HasInvoice": false,
			"ForNames": false
		},
		{
			"ID": 753261,
			"ShopID": 58,
			"Suggestions": null,
			"SKU": "98",
			"IsSKUCorrect": -1,
			"Ignored": false,
			"Name": "צנון",
			"Tags": "[]",
			"Image": null,
			"ProductImage": null,
			"ImageToShow": null,
			"FirstUnitMeasureID": null,
			"FirstUnitMeasureName": null,
			"FirstUnitMeasureDisplayName": null,
			"FirstUnitMeasureNameTranslations": null,
			"FirstUnitWeight": 0,
			"SecondUnitMeasureID": null,
			"SecondUnitMeasureName": null,
			"SecondUnitMeasureDisplayName": null,
			"SecondUnitMeasureNameTranslations": null,
			"SecondUnitWeight": 0,
			"Price": 7.9,
			"OldPrice": null,
			"UnlimitedQuantity": true,
			"Quantity": 0,
			"LowestPriceInShoook": 0,
			"DisplayOrder": null,
			"OrderForPicking": 9999,
			"ShowInStock": false,
			"ProductID": null,
			"ProductName": null,
			"ProductSKU": null,
			"ProductManufacturerName": null,
			"ProductBrandName": null,
			"ManufacturerName": null,
			"ManufacturerID": 0,
			"BrandName": null,
			"BrandID": 0,
			"ShopName": "Opal Market",
			"SoldByWeight": false,
			"PrivateText": null,
			"CommentsForAdmin": null,
			"EnableOverrideGlobal": false,
			"IsMeasuredBySKU": false,
			"Capacity": null,
			"LinkedImages": [],
			"AddNewForm": null,
			"ControllerName": null,
			"Editable": true,
			"Moveable": false,
			"Popup": false,
			"ToggelActive": false,
			"Copy": false,
			"Delete": false,
			"HasInvoice": false,
			"ForNames": false
		},
		{
			"ID": 678338,
			"ShopID": 58,
			"Suggestions": null,
			"SKU": "9800800056",
			"IsSKUCorrect": -1,
			"Ignored": false,
			"Name": "נוטלה טו גו 52ג",
			"Tags": "[{\"id\":191,\"name\":\"חטיפים מתוקים (SweetsSnacks)\"}]",
			"Image": null,
			"ProductImage": null,
			"ImageToShow": null,
			"FirstUnitMeasureID": 3,
			"FirstUnitMeasureName": "Gram",
			"FirstUnitMeasureDisplayName": "גרם",
			"FirstUnitMeasureNameTranslations": null,
			"FirstUnitWeight": 0,
			"SecondUnitMeasureID": null,
			"SecondUnitMeasureName": null,
			"SecondUnitMeasureDisplayName": null,
			"SecondUnitMeasureNameTranslations": null,
			"SecondUnitWeight": 0,
			"Price": 5,
			"OldPrice": "7.00",
			"UnlimitedQuantity": false,
			"Quantity": 0,
			"LowestPriceInShoook": 0,
			"DisplayOrder": null,
			"OrderForPicking": 9999,
			"ShowInStock": false,
			"ProductID": 226102,
			"ProductName": "פררו נוטלה TO GO",
			"ProductSKU": "009800800056",
			"ProductManufacturerName": null,
			"ProductBrandName": "נוטלה",
			"ManufacturerName": null,
			"ManufacturerID": 0,
			"BrandName": null,
			"BrandID": 0,
			"ShopName": "Opal Market",
			"SoldByWeight": false,
			"PrivateText": null,
			"CommentsForAdmin": null,
			"EnableOverrideGlobal": false,
			"IsMeasuredBySKU": false,
			"Capacity": null,
			"LinkedImages": [],
			"AddNewForm": null,
			"ControllerName": null,
			"Editable": true,
			"Moveable": false,
			"Popup": false,
			"ToggelActive": false,
			"Copy": false,
			"Delete": false,
			"HasInvoice": false,
			"ForNames": false
		},
		{
			"ID": 678339,
			"ShopID": 58,
			"Suggestions": null,
			"SKU": "99",
			"IsSKUCorrect": -1,
			"Ignored": false,
			"Name": "פלפל חריף",
			"Tags": "[{\"id\":99,\"name\":\"ירקות טריים (FreshVegetables)\"}]",
			"Image": "פלפלחריף_20230618135900.PNG",
			"ProductImage": null,
			"ImageToShow": "פלפלחריף_20230618135900.PNG",
			"FirstUnitMeasureID": 1,
			"FirstUnitMeasureName": "KG",
			"FirstUnitMeasureDisplayName": "ק״ג",
			"FirstUnitMeasureNameTranslations": null,
			"FirstUnitWeight": 1,
			"SecondUnitMeasureID": null,
			"SecondUnitMeasureName": null,
			"SecondUnitMeasureDisplayName": null,
			"SecondUnitMeasureNameTranslations": null,
			"SecondUnitWeight": 0,
			"Price": 11.9,
			"OldPrice": null,
			"UnlimitedQuantity": true,
			"Quantity": 0,
			"LowestPriceInShoook": 0,
			"DisplayOrder": null,
			"OrderForPicking": 9999,
			"ShowInStock": false,
			"ProductID": 196691,
			"ProductName": "פלפל חריף",
			"ProductSKU": "11180157",
			"ProductManufacturerName": null,
			"ProductBrandName": null,
			"ManufacturerName": null,
			"ManufacturerID": null,
			"BrandName": null,
			"BrandID": null,
			"ShopName": "Opal Market",
			"SoldByWeight": true,
			"PrivateText": null,
			"CommentsForAdmin": null,
			"EnableOverrideGlobal": false,
			"IsMeasuredBySKU": false,
			"Capacity": null,
			"LinkedImages": [
				{
					"ProductInShopID": 678339,
					"Image": "פלפלחריף_20230618135901.PNG",
					"Priority": 0
				}
			],
			"AddNewForm": null,
			"ControllerName": null,
			"Editable": true,
			"Moveable": false,
			"Popup": false,
			"ToggelActive": false,
			"Copy": false,
			"Delete": false,
			"HasInvoice": false,
			"ForNames": false
		},
		{
			"ID": 753529,
			"ShopID": 58,
			"Suggestions": null,
			"SKU": "9958340099583",
			"IsSKUCorrect": -1,
			"Ignored": false,
			"Name": "מסטיק אורביט קטן בטעם פירות",
			"Tags": "[{\"id\":42,\"name\":\"מסטיקים וסוכריות (ChewingGumCandies)\"}]",
			"Image": null,
			"ProductImage": "40099583.png",
			"ImageToShow": "40099583.png",
			"FirstUnitMeasureID": 3,
			"FirstUnitMeasureName": "Gram",
			"FirstUnitMeasureDisplayName": "גרם",
			"FirstUnitMeasureNameTranslations": null,
			"FirstUnitWeight": 0,
			"SecondUnitMeasureID": null,
			"SecondUnitMeasureName": null,
			"SecondUnitMeasureDisplayName": null,
			"SecondUnitMeasureNameTranslations": null,
			"SecondUnitWeight": 0,
			"Price": 2.5,
			"OldPrice": null,
			"UnlimitedQuantity": true,
			"Quantity": 0,
			"LowestPriceInShoook": 0,
			"DisplayOrder": 0,
			"OrderForPicking": 9999,
			"ShowInStock": false,
			"ProductID": 340435,
			"ProductName": "אורביט קטן ילדים",
			"ProductSKU": "9958340099583",
			"ProductManufacturerName": null,
			"ProductBrandName": "אורביט",
			"ManufacturerName": null,
			"ManufacturerID": 0,
			"BrandName": null,
			"BrandID": 0,
			"ShopName": "Opal Market",
			"SoldByWeight": false,
			"PrivateText": "",
			"CommentsForAdmin": null,
			"EnableOverrideGlobal": true,
			"IsMeasuredBySKU": true,
			"Capacity": "13",
			"LinkedImages": [],
			"AddNewForm": null,
			"ControllerName": null,
			"Editable": true,
			"Moveable": false,
			"Popup": false,
			"ToggelActive": false,
			"Copy": false,
			"Delete": false,
			"HasInvoice": false,
			"ForNames": false
		}
	],
	"draw": "25",
	"recordsTotal": 3614,
	"recordsFiltered": 3614
}
